jsonapi/serializers.py
jsonapi/utils.py
jsonapi/api.py
jsonapi/statuses.py
jsonapi/models.py
jsonapi/exceptions.py
jsonapi/request_parser.py
jsonapi/__init__.py
jsonapi/django_utils.py
jsonapi/auth.py
jsonapi/signals.py
jsonapi/six.py
jsonapi/resource.py
jsonapi/model_inspector.py
jsonapi/templates/jsonapi/index.html
jsonapi/static/jsonapi/bootstrap.min.css
jsonapi/static/jsonapi/main.css
jsonapi/static/jsonapi/highlight.min.css
jsonapi/static/jsonapi/highlight.min.js
jsonapi-0.9.9.dist-info/top_level.txt
jsonapi-0.9.9.dist-info/METADATA
jsonapi-0.9.9.dist-info/metadata.json
jsonapi-0.9.9.dist-info/RECORD
jsonapi-0.9.9.dist-info/DESCRIPTION.rst
jsonapi-0.9.9.dist-info/pbr.json
jsonapi-0.9.9.dist-info/WHEEL
